yad80/__init__.py
yad80/__main__.py
yad80/cli.py
yad80/disasm.py
yad80/eager.py
yad80/exceptions.py
yad80/loader.py
yad80/memory.py
yad80/mnemonic.py
yad80/mnemonic_cb.py
yad80/mnemonic_dd_fd.py
yad80/mnemonic_defs.py
yad80/mnemonic_ed.py
yad80-0.2.1.dist-info/LICENSE
yad80-0.2.1.dist-info/METADATA
yad80-0.2.1.dist-info/WHEEL
yad80-0.2.1.dist-info/entry_points.txt
yad80-0.2.1.dist-info/top_level.txt
yad80-0.2.1.dist-info/RECORD
