Metadata-Version: 2.1
Name: yad80
Version: 0.2.1
Summary: Yet Another Disassembler for Z80
Author-email: dogatana <dogatana@gmail.com>
Project-URL: Homepage, https://github.com/dogatana/yad80
Project-URL: Bug Tracker, https://github.com/dogatana/yad80/issues
Classifier: Programming Language :: Python :: 3
Classifier: License :: OSI Approved :: MIT License
Classifier: Operating System :: OS Independent
Classifier: Development Status :: 5 - Production/Stable
Classifier: Topic :: Software Development :: Disassemblers
Requires-Python: >=3.10
License-File: LICENSE
Provides-Extra: dev
Requires-Dist: build; extra == "dev"
Requires-Dist: twine; extra == "dev"
